manakit_mantine/__init__.py
manakit_mantine/action_icon.py
manakit_mantine/autocomplete.py
manakit_mantine/base.py
manakit_mantine/button.py
manakit_mantine/date.py
manakit_mantine/inputs.py
manakit_mantine/json_input.py
manakit_mantine/mantine_provider.js
manakit_mantine/masked_input.py
manakit_mantine/multi_select.py
manakit_mantine/nav_link.py
manakit_mantine/navigation_progress.js
manakit_mantine/nprogress.py
manakit_mantine/number_formatter.py
manakit_mantine/number_input.py
manakit_mantine/password_input.py
manakit_mantine/scroll_area.py
manakit_mantine/select.py
manakit_mantine/table.py
manakit_mantine/tags_input.py
manakit_mantine/textarea.py
manakit_mantine/tiptap.py
manakit_mantine/tiptap_wrapper.js
manakit_mantine-0.3.1.dist-info/METADATA
manakit_mantine-0.3.1.dist-info/WHEEL
manakit_mantine-0.3.1.dist-info/RECORD
