Metadata-Version: 2.4
Name: manakit-mantine
Version: 0.3.1
Summary: Mantine UI input components for Reflex with type safety and comprehensive examples
Project-URL: Homepage, https://github.com/jenreh/manakit
Project-URL: Documentation, https://github.com/jenreh/manakit/tree/main/docs
Project-URL: Repository, https://github.com/jenreh/manakit
Project-URL: Issues, https://github.com/jenreh/manakit/issues
License: MIT
Keywords: components,forms,input,mantine,react,reflex,ui,web
Classifier: Development Status :: 3 - Alpha
Classifier: Framework :: AsyncIO
Classifier: Intended Audience :: Developers
Classifier: License :: OSI Approved :: MIT License
Classifier: Programming Language :: Python :: 3
Classifier: Programming Language :: Python :: 3.12
Classifier: Topic :: Software Development :: Libraries :: Python Modules
Classifier: Topic :: Software Development :: User Interfaces
Requires-Python: >=3.12
Requires-Dist: reflex>=0.8.12
